README.rst
setup.py
test/test_basic_functionality.py
test/test_import.py
test/test_simple_seeking.py
videosequence/__init__.py
videosequence.egg-info/PKG-INFO
videosequence.egg-info/SOURCES.txt
videosequence.egg-info/dependency_links.txt
videosequence.egg-info/requires.txt
videosequence.egg-info/top_level.txt