Metadata-Version: 1.1
Name: videosequence
Version: 1.1.0
Summary: Read from and seek into video files as if they were Python sequences of PIL.Image-s.
Home-page: https://github.com/rjw57/videosequence
Author: Rich Wareham
Author-email: rich.videosequence@richwareham.com
License: MIT
Platform: UNKNOWN
Classifier: Development Status :: 4 - Beta
Classifier: Environment :: Console
Classifier: Intended Audience :: Developers
Classifier: Intended Audience :: Science/Research
Classifier: License :: OSI Approved :: MIT License
Classifier: Operating System :: POSIX
Classifier: Topic :: Multimedia :: Video
Classifier: Programming Language :: Python :: 2
Classifier: Programming Language :: Python :: 3
